dualram.v
module raminfr
(clk1,clk2, wea, addra, addrb, dia,dib,web, doa, dob);

input clk1;
input clk2;
input wea;
input web;
input [3:0] addra;
input [3:0] addrb;
input [3:0] dia;
input [3:0] dib;
output [3:0] doa;
output [3:0] dob;
reg [3:0] ram [31:0];
reg [3:0] read_addra;
reg [3:0] read_addrb;
always@(posedge clk1) begin
    if (wea) begin
        ram[addra] <= dia;
    end
    read_addra <= addra;
end
always @(posedge clk2) begin
    if (web) begin
        ram[addrb] <= dib;
    end
    read_addrb <= addrb;
end
assign dob = ram[read_addrb];
assign doa = ram[read_addra];
endmodule

test.v
module pff;

reg clk1;
reg clk2;
reg wea;
reg [3:0] addra;
reg [3:0] addrb;
reg [3:0] dia;
reg [3:0] dib;
reg web;
wire [3:0] doa;
wire [3:0] dob;
raminfr uut (
    .clk1(clk1),
    .clk2(clk2),
    .wea(wea),
    .addra(addra),
    .addrb(addrb),
    .dia(dia),
    .dib(dib),
    .web(web),
    .doa(doa),
    .dob(dob)
);

initial begin

    clk1 = 0;
    clk2 = 0;
    wea = 0;
    web = 0;
    addra = 0;
    addrb = 0;
    dia = 0;
    dib = 0;

    forever begin
        #3 clk1=~clk1;
        #1 clk2=~clk2;
    end
end

initial begin
    wea=1;
    web=1;
    addrb=4'd7;
    addra=4'd6;
    dia=4'ha;
    dib=4'hb;
    #5
    dia=4'hc;
    dib=4'hd;

    #10
    wea=0;
    web=0;
    addra=4'd6;
    addrb=4'd7;
    dia=4'ha;
    dib=4'hb;
    #5
    dia=4'hc;
    dib=4'hd;

    #10
    wea=1;
    web=0;
    addra=4'd2;
    addrb=4'd9;
    dia=4'h0;
    dib=4'h1;

    #10
    wea=0;
    web=1;
    addra=4'd2;
    addrb=4'd9;
    dia=4'h0;
    dib=4'h1;
    #10 $finish;
end

initial begin
    $dumpfile("bleh.vcd");
    $dumpvars(0,pff);
end


endmodule

bleh.vcd
$date
	Wed Nov 22 10:53:25 2023
$end
$version
	Icarus Verilog
$end
$timescale
	1s
$end
$scope module pff $end
$var wire 4 ! dob [3:0] $end
$var wire 4 " doa [3:0] $end
$var reg 4 # addra [3:0] $end
$var reg 4 $ addrb [3:0] $end
$var reg 1 % clk1 $end
$var reg 1 & clk2 $end
$var reg 4 ' dia [3:0] $end
$var reg 4 ( dib [3:0] $end
$var reg 1 ) wea $end
$var reg 1 * web $end
$scope module uut $end
$var wire 4 + addra [3:0] $end
$var wire 4 , addrb [3:0] $end
$var wire 1 % clk1 $end
$var wire 1 & clk2 $end
$var wire 4 - dia [3:0] $end
$var wire 4 . dib [3:0] $end
$var wire 4 / doa [3:0] $end
$var wire 4 0 dob [3:0] $end
$var wire 1 ) wea $end
$var wire 1 * web $end
$var reg 4 1 read_addra [3:0] $end
$var reg 4 2 read_addrb [3:0] $end
$upscope $end
$upscope $end
$enddefinitions $end
$comment Show the parameter values. $end
$dumpall
$end
#0
$dumpvars
bx 2
bx 1
bx 0
bx /
b1011 .
b1010 -
b111 ,
b110 +
1*
1)
b1011 (
b1010 '
0&
0%
b111 $
b110 #
bx "
bx !
$end
#3
b1010 "
b1010 /
b110 1
1%
#4
b1011 !
b1011 0
b111 2
1&
#5
b1101 (
b1101 .
b1100 '
b1100 -
#7
0%
#8
0&
#11
b1100 "
b1100 /
1%
#12
b1101 !
b1101 0
1&
#15
0%
b1011 (
b1011 .
b1010 '
b1010 -
0*
0)
#16
0&
#19
1%
#20
1&
b1101 (
b1101 .
b1100 '
b1100 -
#23
0%
#24
0&
#27
1%
#28
1&
#30
b1 (
b1 .
b0 '
b0 -
b1001 $
b1001 ,
b10 #
b10 +
1)
#31
0%
#32
0&
#35
b0 "
b0 /
b10 1
1%
#36
bx !
bx 0
b1001 2
1&
#39
0%
#40
0&
1*
0)
#43
1%
#44
b1 !
b1 0
1&
